gotify_tray/__init__.py
gotify_tray/__main__.py
gotify_tray/__version__.py
gotify_tray/tasks.py
gotify_tray/utils.py
gotify_tray/database/__init__.py
gotify_tray/database/cache.py
gotify_tray/database/database.py
gotify_tray/database/default_settings.py
gotify_tray/database/downloader.py
gotify_tray/database/settings.py
gotify_tray/gotify/__init__.py
gotify_tray/gotify/api.py
gotify_tray/gotify/listener.py
gotify_tray/gotify/models.py
gotify_tray/gui/MainApplication.py
gotify_tray/gui/__init__.py
gotify_tray/gui/designs/__init__.py
gotify_tray/gui/designs/widget_main.py
gotify_tray/gui/designs/widget_message.py
gotify_tray/gui/designs/widget_server.py
gotify_tray/gui/designs/widget_settings.py
gotify_tray/gui/images/__init__.py
gotify_tray/gui/images/gotify-small-macos.png
gotify_tray/gui/images/gotify-small.png
gotify_tray/gui/images/logo-macos.ico
gotify_tray/gui/images/logo.ico
gotify_tray/gui/images/qt.png
gotify_tray/gui/images/tray-error-macos.png
gotify_tray/gui/images/tray-error.png
gotify_tray/gui/images/tray-macos.png
gotify_tray/gui/images/tray-unread-macos.png
gotify_tray/gui/images/tray-unread.png
gotify_tray/gui/images/tray.png
gotify_tray/gui/models/ApplicationModel.py
gotify_tray/gui/models/MessagesModel.py
gotify_tray/gui/models/__init__.py
gotify_tray/gui/themes/__init__.py
gotify_tray/gui/themes/base.qss
gotify_tray/gui/themes/dark/refresh.svg
gotify_tray/gui/themes/dark/status_active.svg
gotify_tray/gui/themes/dark/status_connecting.svg
gotify_tray/gui/themes/dark/status_error.svg
gotify_tray/gui/themes/dark/status_inactive.svg
gotify_tray/gui/themes/dark/style.qss
gotify_tray/gui/themes/dark/trashcan.svg
gotify_tray/gui/themes/light/refresh.svg
gotify_tray/gui/themes/light/status_active.svg
gotify_tray/gui/themes/light/status_connecting.svg
gotify_tray/gui/themes/light/status_error.svg
gotify_tray/gui/themes/light/status_inactive.svg
gotify_tray/gui/themes/light/style.qss
gotify_tray/gui/themes/light/trashcan.svg
gotify_tray-0.5.3.dist-info/LICENSE
gotify_tray-0.5.3.dist-info/METADATA
gotify_tray-0.5.3.dist-info/WHEEL
gotify_tray-0.5.3.dist-info/entry_points.txt
gotify_tray-0.5.3.dist-info/top_level.txt
gotify_tray-0.5.3.dist-info/RECORD
