Metadata-Version: 2.1
Name: gotify-tray
Version: 0.5.3
Summary: A tray notification application for receiving messages from a Gotify server.
Home-page: https://github.com/seird/gotify-tray
Author: k.dries@protonmail.com
Author-email: k.dries@protonmail.com
License: GPLv3
Classifier: License :: OSI Approved :: GNU General Public License v3 (GPLv3)
Classifier: Programming Language :: Python
Classifier: Programming Language :: Python :: 3
Classifier: Programming Language :: Python :: 3.10
Classifier: Programming Language :: Python :: 3.11
Classifier: Programming Language :: Python :: 3.12
Classifier: Programming Language :: Python :: 3.13
Requires-Python: >=3.10.0
License-File: LICENSE
Requires-Dist: requests
Requires-Dist: pyqt6 >=6.7.1
